MANIFEST.in
README.md
requirements.txt
requirements_extra.txt
setup.py
RedditWallpaperChooser/__init__.py
RedditWallpaperChooser/config.py
RedditWallpaperChooser/constants.py
RedditWallpaperChooser/main.py
RedditWallpaperChooser/manager.py
RedditWallpaperChooser/reddit.py
RedditWallpaperChooser/utils.py
RedditWallpaperChooser/wallpaper.py
RedditWallpaperChooser.egg-info/PKG-INFO
RedditWallpaperChooser.egg-info/SOURCES.txt
RedditWallpaperChooser.egg-info/dependency_links.txt
RedditWallpaperChooser.egg-info/not-zip-safe
RedditWallpaperChooser.egg-info/requires.txt
RedditWallpaperChooser.egg-info/top_level.txt
bin/reddit-wallpaper-chooser