Metadata-Version: 1.1
Name: RedditWallpaperChooser
Version: 0.2.3
Summary: Automatically download trending wallpapers from subreddits of your choice.
Home-page: https://github.com/aldur/RedditWallpaperChooser
Author: aldur
Author-email: adrianodl@hotmail.it
License: MIT
Download-URL: https://github.com/aldur/RedditWallpaperChooser/releases/
Keywords: Reddit subreddit wallpaper desktop
Platform: any
Classifier: Development Status :: 5 - Production/Stable
Classifier: Environment :: Console
Classifier: Intended Audience :: End Users/Desktop
Classifier: Intended Audience :: System Administrators
Classifier: License :: OSI Approved :: MIT License
Classifier: Programming Language :: Python :: 3 :: Only
Classifier: Programming Language :: Python :: 3.5
Classifier: Topic :: Desktop Environment
Classifier: Topic :: Multimedia
Classifier: Topic :: Utilities
